termtyper/config.json
termtyper/term_typer.py
termtyper/update.json
termtyper/wpm_statistics.json
termtyper/data/ccpp.txt
termtyper/data/chash.txt
termtyper/data/frozen.txt
termtyper/data/go.txt
termtyper/data/happy_feet.txt
termtyper/data/harry_potter.txt
termtyper/data/html.txt
termtyper/data/java.txt
termtyper/data/java_script.txt
termtyper/data/kotlin.txt
termtyper/data/kungfu_panda.txt
termtyper/data/lotr.txt
termtyper/data/moana.txt
termtyper/data/php.txt
termtyper/data/python.txt
termtyper/data/ruby.txt
termtyper/data/rust.txt
termtyper/data/shrek.txt
termtyper/data/swift.txt
termtyper/data/titanic.txt
termtyper/data/top1000.txt
termtyper/data/top200.txt
termtyper/data/top500.txt
termtyper/data/toy_story.txt
termtyper-2.0.5.dist-info/LICENSE
termtyper-2.0.5.dist-info/METADATA
termtyper-2.0.5.dist-info/WHEEL
termtyper-2.0.5.dist-info/entry_points.txt
termtyper-2.0.5.dist-info/top_level.txt
termtyper-2.0.5.dist-info/RECORD
