Metadata-Version: 2.1
Name: termtyper
Version: 2.0.5
Summary: A Terminal based typing practice application
Home-page: https://github.com/nagesh1805/termtyper.git
Author: Nagesh Talagani
Author-email: nageshmath@gmail.com
License: UNKNOWN
Platform: UNKNOWN
Requires-Python: >=3.7
License-File: LICENSE
Requires-Dist: windows-curses ; platform_system == "Windows"
